django_zurb_foundation_rtl-6.0.6.3.dist-info/DESCRIPTION.rst
django_zurb_foundation_rtl-6.0.6.3.dist-info/METADATA
django_zurb_foundation_rtl-6.0.6.3.dist-info/metadata.json
django_zurb_foundation_rtl-6.0.6.3.dist-info/RECORD
django_zurb_foundation_rtl-6.0.6.3.dist-info/top_level.txt
django_zurb_foundation_rtl-6.0.6.3.dist-info/WHEEL
foundation/create_partials.py
foundation/urls.py
foundation/__init__.py
foundation/static/foundation/css/foundation-icons.css
foundation/static/foundation/css/foundation-icons.eot
foundation/static/foundation/css/foundation-icons.svg
foundation/static/foundation/css/foundation-icons.ttf
foundation/static/foundation/css/foundation-icons.woff
foundation/static/foundation/css/foundation-rtl.css
foundation/static/foundation/css/foundation.css
foundation/static/foundation/css/normalize.css
foundation/static/foundation/js/foundation.js
foundation/static/foundation/js/foundation.min.js
foundation/static/foundation/js/foundation/foundation.abide.js
foundation/static/foundation/js/foundation/foundation.accordion.js
foundation/static/foundation/js/foundation/foundation.accordionMenu.js
foundation/static/foundation/js/foundation/foundation.core.js
foundation/static/foundation/js/foundation/foundation.drilldown.js
foundation/static/foundation/js/foundation/foundation.dropdown.js
foundation/static/foundation/js/foundation/foundation.dropdownMenu.js
foundation/static/foundation/js/foundation/foundation.equalizer.js
foundation/static/foundation/js/foundation/foundation.interchange.js
foundation/static/foundation/js/foundation/foundation.magellan.js
foundation/static/foundation/js/foundation/foundation.offcanvas.js
foundation/static/foundation/js/foundation/foundation.orbit.js
foundation/static/foundation/js/foundation/foundation.responsiveMenu.js
foundation/static/foundation/js/foundation/foundation.responsiveToggle.js
foundation/static/foundation/js/foundation/foundation.reveal.js
foundation/static/foundation/js/foundation/foundation.slider.js
foundation/static/foundation/js/foundation/foundation.sticky.js
foundation/static/foundation/js/foundation/foundation.tabs.js
foundation/static/foundation/js/foundation/foundation.toggler.js
foundation/static/foundation/js/foundation/foundation.tooltip.js
