Metadata-Version: 2.0
Name: django-zurb-foundation-rtl
Version: 6.0.6.3
Summary: Django Zurb Foundation package + RTL Support
Home-page: https://github.com/wtayyeb/django-zurb-foundation-rtl
Author: W. Tayyeb
Author-email: w.tayyeb@gmail.com
License: BSD License
Platform: UNKNOWN
Classifier: Environment :: Web Environment
Classifier: Framework :: Django
Classifier: Intended Audience :: Developers
Classifier: License :: OSI Approved :: BSD License
Classifier: Operating System :: OS Independent
Classifier: Programming Language :: Python
Classifier: Programming Language :: Python :: 2
Classifier: Programming Language :: Python :: 3
Classifier: Topic :: Utilities
